dailalib/__init__.py
dailalib/__main__.py
dailalib/configuration.py
dailalib/daila_plugin.py
dailalib/installer.py
dailalib/api/__init__.py
dailalib/api/ai_api.py
dailalib/api/litellm/__init__.py
dailalib/api/litellm/config_dialog.py
dailalib/api/litellm/litellm_api.py
dailalib/api/litellm/prompt_type.py
dailalib/api/litellm/prompts/__init__.py
dailalib/api/litellm/prompts/cot_prompts.py
dailalib/api/litellm/prompts/few_shot_prompts.py
dailalib/api/litellm/prompts/prompt.py
dailalib/binsync_plugin/__init__.py
dailalib/binsync_plugin/ai_bs_user.py
dailalib/binsync_plugin/ai_user_config_ui.py
dailalib/binsync_plugin/openai_bs_user.py
dailalib/binsync_plugin/varmodel_bs_user.py
dailalib/llm_chat/__init__.py
dailalib/llm_chat/binja.py
dailalib/llm_chat/ida.py
dailalib/llm_chat/llm_chat_ui.py
dailalib-3.18.0.dist-info/METADATA
dailalib-3.18.0.dist-info/WHEEL
dailalib-3.18.0.dist-info/entry_points.txt
dailalib-3.18.0.dist-info/top_level.txt
dailalib-3.18.0.dist-info/RECORD
