Metadata-Version: 2.4
Name: dailalib
Version: 3.18.0
Summary: The Decompiler Artificial Intelligence Language Assistant (DAILA) is a tool for adding AI to decompilers.
Home-page: https://github.com/mahaloz/DAILA
License: BSD 2 Clause
Classifier: License :: OSI Approved :: BSD License
Classifier: Programming Language :: Python :: 3
Classifier: Programming Language :: Python :: 3.10
Requires-Python: >=3.10
Requires-Dist: litellm>=1.44.27
Requires-Dist: tiktoken
Requires-Dist: Jinja2
Requires-Dist: libbs[ghidra]>=2.10.0
Provides-Extra: full
Requires-Dist: varbert>=2.3.0; extra == "full"
Requires-Dist: PySide6-Essentials>=6.4.2; extra == "full"
